keras_mml/__init__.py
keras_mml/layers/__init__.py
keras_mml/layers/activations/__init__.py
keras_mml/layers/activations/bilinear.py
keras_mml/layers/activations/geglu.py
keras_mml/layers/activations/glu.py
keras_mml/layers/activations/reglu.py
keras_mml/layers/activations/seglu.py
keras_mml/layers/activations/swiglu.py
keras_mml/layers/core/__init__.py
keras_mml/layers/core/_dense_impl/__init__.py
keras_mml/layers/core/_dense_impl/backend_dense.py
keras_mml/layers/core/_dense_impl/base_dense.py
keras_mml/layers/core/_dense_impl/jax_dense.py
keras_mml/layers/core/_dense_impl/tensorflow_dense.py
keras_mml/layers/core/_dense_impl/torch_dense.py
keras_mml/layers/core/dense.py
keras_mml/layers/core/embedding.py
keras_mml/layers/misc/__init__.py
keras_mml/layers/misc/patches.py
keras_mml/layers/normalizations/__init__.py
keras_mml/layers/normalizations/rms_norm.py
keras_mml/layers/recurrent/__init__.py
keras_mml/layers/recurrent/gru.py
keras_mml/layers/recurrent/lru.py
keras_mml/layers/recurrent/rnn.py
keras_mml/layers/transformer/__init__.py
keras_mml/layers/transformer/attention.py
keras_mml/layers/transformer/transformer.py
keras_mml/utils/__init__.py
keras_mml/utils/array/__init__.py
keras_mml/utils/array/encoding.py
keras_mml/utils/array/ternary_multiplication.py
keras_mml/utils/misc/__init__.py
keras_mml/utils/misc/coverage.py
keras_mml/utils/misc/number.py
keras_matmulless-0.1.2.dist-info/LICENSE
keras_matmulless-0.1.2.dist-info/METADATA
keras_matmulless-0.1.2.dist-info/WHEEL
keras_matmulless-0.1.2.dist-info/RECORD
