Metadata-Version: 2.3
Name: keras-matmulless
Version: 0.1.2
Summary: Keras layers without using matrix multiplications.
License: Apache-2.0
Keywords: tensorflow,pytorch,jax,keras,machine learning
Author: PhotonicGluon
Author-email: 25820201+PhotonicGluon@users.noreply.github.com
Requires-Python: >=3.9.2,<3.13
Classifier: Development Status :: 3 - Alpha
Classifier: Intended Audience :: Science/Research
Classifier: License :: OSI Approved :: Apache Software License
Classifier: Operating System :: MacOS
Classifier: Operating System :: Unix
Classifier: Programming Language :: Python :: 3
Classifier: Programming Language :: Python :: 3.10
Classifier: Programming Language :: Python :: 3.11
Classifier: Programming Language :: Python :: 3.12
Classifier: Programming Language :: Python :: 3 :: Only
Classifier: Programming Language :: Python :: 3.9
Classifier: Topic :: Scientific/Engineering
Classifier: Topic :: Software Development
Requires-Dist: cryptography (>=44.0.2,<45.0.0)
Requires-Dist: einops (>=0.8.0,<0.9.0)
Requires-Dist: jaxtyping (>=0.2.31,<0.3.0)
Requires-Dist: keras (>=3.3.3,<4.0.0)
Requires-Dist: ml-dtypes (>=0.3.1,<0.4.0)
Requires-Dist: numpy (>=1.23.5,<2.0.0) ; python_version < "3.12"
Requires-Dist: numpy (>=1.26.0,<2.0.0) ; python_version >= "3.12"
Requires-Dist: poetry-dynamic-versioning[plugin] (>=1.4.0,<2.0.0)
